{
    "text_lines": [
        {
            "text": "new competitive products",
            "bbox": [
                297.0,
                62.0,
                512.0,
                77.0
            ]
        },
        {
            "text": "REPORTED BY: C. M. WIECHMANN, D.M., LUBBOCK, TX",
            "bbox": [
                61.0,
                121.0,
                496.0,
                138.0
            ]
        },
        {
            "text": "DATE: 10/5/92 TIME:",
            "bbox": [
                114.0,
                170.0,
                351.0,
                194.0
            ]
        },
        {
            "text": "R. J. REYNOLDS",
            "bbox": [
                228.0,
                223.0,
                359.0,
                242.0
            ]
        },
        {
            "text": "MANUFACTURER:",
            "bbox": [
                63.0,
                227.0,
                190.0,
                243.0
            ]
        },
        {
            "text": "",
            "bbox": [
                217.0,
                227.0,
                231.0,
                240.0
            ]
        },
        {
            "text": "BRAND NAME: CARDINAL CIGARETTES (11 PACKINGS)",
            "bbox": [
                62.0,
                278.0,
                508.0,
                301.0
            ]
        },
        {
            "text": "TYPE OF",
            "bbox": [
                63.0,
                332.0,
                126.0,
                349.0
            ]
        },
        {
            "text": "PRODUCT:",
            "bbox": [
                63.0,
                350.0,
                141.0,
                366.0
            ]
        },
        {
            "text": "SIZE OR SIZES:",
            "bbox": [
                64.0,
                402.0,
                173.0,
                417.0
            ]
        },
        {
            "text": "LIST PRICE: ",
            "bbox": [
                63.0,
                454.0,
                150.0,
                470.0
            ]
        },
        {
            "text": "EXTENT OF",
            "bbox": [
                64.0,
                506.0,
                145.0,
                522.0
            ]
        },
        {
            "text": "DISTRIBUTION:",
            "bbox": [
                64.0,
                523.0,
                173.0,
                539.0
            ]
        },
        {
            "text": "OTHER",
            "bbox": [
                65.0,
                610.0,
                117.0,
                626.0
            ]
        },
        {
            "text": "SEE ATTACHMENT",
            "bbox": [
                234.0,
                626.0,
                365.0,
                643.0
            ]
        },
        {
            "text": "INFORMATION:",
            "bbox": [
                65.0,
                628.0,
                172.0,
                645.0
            ]
        },
        {
            "text": "cc:",
            "bbox": [
                65.0,
                750.0,
                92.0,
                766.0
            ]
        },
        {
            "text": "K. P. Augustyn",
            "bbox": [
                531.0,
                764.0,
                634.0,
                780.0
            ]
        },
        {
            "text": "J. J. Tatulli",
            "bbox": [
                354.0,
                765.0,
                432.0,
                781.0
            ]
        },
        {
            "text": "F. J. Schultz",
            "bbox": [
                221.0,
                766.0,
                311.0,
                782.0
            ]
        },
        {
            "text": "A. H. Tisch",
            "bbox": [
                65.0,
                767.0,
                143.0,
                783.0
            ]
        },
        {
            "text": "L. H. Kersh",
            "bbox": [
                354.0,
                783.0,
                435.0,
                799.0
            ]
        },
        {
            "text": "V. D. Lindsley",
            "bbox": [
                530.0,
                782.0,
                628.0,
                798.0
            ]
        },
        {
            "text": "A. W. Spears",
            "bbox": [
                221.0,
                784.0,
                315.0,
                800.0
            ]
        },
        {
            "text": "R. H. Orcutt",
            "bbox": [
                65.0,
                785.0,
                148.0,
                800.0
            ]
        },
        {
            "text": "J. R. Slater",
            "bbox": [
                354.0,
                800.0,
                432.0,
                816.0
            ]
        },
        {
            "text": "R. D. Hammer",
            "bbox": [
                531.0,
                800.0,
                630.0,
                815.0
            ]
        },
        {
            "text": "N. P. Ruffalo",
            "bbox": [
                221.0,
                801.0,
                312.0,
                817.0
            ]
        },
        {
            "text": "M. A. Peterson",
            "bbox": [
                64.0,
                803.0,
                171.0,
                818.0
            ]
        },
        {
            "text": "A. Pasheluk",
            "bbox": [
                354.0,
                818.0,
                438.0,
                834.0
            ]
        },
        {
            "text": "T. L. Achey",
            "bbox": [
                221.0,
                819.0,
                303.0,
                835.0
            ]
        },
        {
            "text": "M. L. Orlowsky",
            "bbox": [
                65.0,
                820.0,
                171.0,
                836.0
            ]
        },
        {
            "text": "E6619E16",
            "bbox": [
                732.0,
                827.0,
                753.0,
                897.0
            ]
        },
        {
            "text": "R. S. Goldbrenner",
            "bbox": [
                354.0,
                835.0,
                480.0,
                851.0
            ]
        },
        {
            "text": "P. J. McCann",
            "bbox": [
                222.0,
                836.0,
                317.0,
                853.0
            ]
        },
        {
            "text": "L. Gordon",
            "bbox": [
                65.0,
                838.0,
                136.0,
                852.0
            ]
        },
        {
            "text": "N. Simeonidis",
            "bbox": [
                354.0,
                853.0,
                452.0,
                869.0
            ]
        },
        {
            "text": "A. J. Giacoio",
            "bbox": [
                222.0,
                854.0,
                312.0,
                870.0
            ]
        },
        {
            "text": "G. Telford",
            "bbox": [
                65.0,
                855.0,
                136.0,
                871.0
            ]
        },
        {
            "text": "S. F. Smith",
            "bbox": [
                355.0,
                870.0,
                432.0,
                887.0
            ]
        }
    ],
    "image_bbox": [
        0.0,
        0.0,
        781.0,
        1000.0
    ]
}