{
    "text_lines": [
        {
            "line_text": "NEW COMPETITIVE PRODUCTS",
            "line_bbox": [
                297.0,
                61.0,
                512.0,
                78.0
            ],
            "handwriting": 0,
            "words": [
                {
                    "text": "NEW",
                    "bbox": [
                        298.0,
                        63.0,
                        325.0,
                        79.0
                    ]
                },
                {
                    "text": "COMPETITIVE",
                    "bbox": [
                        334.0,
                        61.0,
                        427.0,
                        78.0
                    ]
                },
                {
                    "text": "PRODUCTS",
                    "bbox": [
                        430.0,
                        61.0,
                        508.0,
                        77.0
                    ]
                }
            ]
        },
        {
            "line_text": "REPORTED BY: C. M. WIECHMANN, D.M. , LUBBOCK, TX",
            "line_bbox": [
                63.0,
                119.0,
                492.0,
                138.0
            ],
            "handwriting": 0,
            "words": [
                {
                    "text": "REPORTED",
                    "bbox": [
                        65.0,
                        122.0,
                        137.0,
                        138.0
                    ]
                },
                {
                    "text": "BY:",
                    "bbox": [
                        141.0,
                        122.0,
                        170.0,
                        138.0
                    ]
                },
                {
                    "text": "C.",
                    "bbox": [
                        185.0,
                        122.0,
                        207.0,
                        138.0
                    ]
                },
                {
                    "text": "M.",
                    "bbox": [
                        211.0,
                        122.0,
                        234.0,
                        138.0
                    ]
                },
                {
                    "text": "WIECHMANN,",
                    "bbox": [
                        238.0,
                        121.0,
                        331.0,
                        138.0
                    ]
                },
                {
                    "text": "D.M.",
                    "bbox": [
                        336.0,
                        121.0,
                        372.0,
                        137.0
                    ]
                },
                {
                    "text": ",",
                    "bbox": [
                        375.0,
                        120.0,
                        384.0,
                        137.0
                    ]
                },
                {
                    "text": "LUBBOCK,",
                    "bbox": [
                        390.0,
                        120.0,
                        464.0,
                        137.0
                    ]
                },
                {
                    "text": "TX",
                    "bbox": [
                        471.0,
                        120.0,
                        489.0,
                        136.0
                    ]
                }
            ]
        },
        {
            "line_text": "DATE: 10/5/92 TIME:",
            "line_bbox": [
                115.0,
                173.0,
                283.0,
                189.0
            ],
            "handwriting": 0,
            "words": [
                {
                    "text": "DATE:",
                    "bbox": [
                        116.0,
                        173.0,
                        162.0,
                        190.0
                    ]
                },
                {
                    "text": "10/5/92",
                    "bbox": [
                        168.0,
                        173.0,
                        232.0,
                        189.0
                    ]
                },
                {
                    "text": "TIME:",
                    "bbox": [
                        245.0,
                        173.0,
                        283.0,
                        189.0
                    ]
                }
            ]
        },
        {
            "line_text": "MANUFACTURER:",
            "line_bbox": [
                63.0,
                227.0,
                186.0,
                242.0
            ],
            "handwriting": 0,
            "words": [
                {
                    "text": "MANUFACTURER:",
                    "bbox": [
                        64.0,
                        227.0,
                        186.0,
                        242.0
                    ]
                }
            ]
        },
        {
            "line_text": "R. J. REYNOLDS",
            "line_bbox": [
                231.0,
                222.0,
                358.0,
                240.0
            ],
            "handwriting": 0,
            "words": [
                {
                    "text": "R.",
                    "bbox": [
                        231.0,
                        225.0,
                        251.0,
                        241.0
                    ]
                },
                {
                    "text": "J.",
                    "bbox": [
                        257.0,
                        224.0,
                        278.0,
                        240.0
                    ]
                },
                {
                    "text": "REYNOLDS",
                    "bbox": [
                        284.0,
                        223.0,
                        357.0,
                        240.0
                    ]
                }
            ]
        },
        {
            "line_text": "BRAND NAME:",
            "line_bbox": [
                64.0,
                279.0,
                162.0,
                295.0
            ],
            "handwriting": 0,
            "words": [
                {
                    "text": "BRAND",
                    "bbox": [
                        65.0,
                        280.0,
                        111.0,
                        295.0
                    ]
                },
                {
                    "text": "NAME:",
                    "bbox": [
                        115.0,
                        280.0,
                        162.0,
                        295.0
                    ]
                }
            ]
        },
        {
            "line_text": "CARDINAL CIGARETTES",
            "line_bbox": [
                197.0,
                281.0,
                367.0,
                298.0
            ],
            "handwriting": 0,
            "words": [
                {
                    "text": "CARDINAL",
                    "bbox": [
                        198.0,
                        283.0,
                        267.0,
                        298.0
                    ]
                },
                {
                    "text": "CIGARETTES",
                    "bbox": [
                        276.0,
                        281.0,
                        366.0,
                        298.0
                    ]
                }
            ]
        },
        {
            "line_text": "(11 PACKINGS)",
            "line_bbox": [
                386.0,
                280.0,
                499.0,
                296.0
            ],
            "handwriting": 0,
            "words": [
                {
                    "text": "(11",
                    "bbox": [
                        386.0,
                        281.0,
                        411.0,
                        297.0
                    ]
                },
                {
                    "text": "PACKINGS)",
                    "bbox": [
                        418.0,
                        281.0,
                        499.0,
                        296.0
                    ]
                }
            ]
        },
        {
            "line_text": "TYPE OF",
            "line_bbox": [
                64.0,
                331.0,
                124.0,
                347.0
            ],
            "handwriting": 0,
            "words": [
                {
                    "text": "TYPE",
                    "bbox": [
                        66.0,
                        332.0,
                        98.0,
                        347.0
                    ]
                },
                {
                    "text": "OF",
                    "bbox": [
                        103.0,
                        331.0,
                        123.0,
                        347.0
                    ]
                }
            ]
        },
        {
            "line_text": "PRODUCT:",
            "line_bbox": [
                64.0,
                349.0,
                140.0,
                365.0
            ],
            "handwriting": 0,
            "words": [
                {
                    "text": "PRODUCT:",
                    "bbox": [
                        65.0,
                        350.0,
                        140.0,
                        365.0
                    ]
                }
            ]
        },
        {
            "line_text": "SIZE OR SIZES:",
            "line_bbox": [
                65.0,
                401.0,
                171.0,
                417.0
            ],
            "handwriting": 0,
            "words": [
                {
                    "text": "SIZE",
                    "bbox": [
                        67.0,
                        402.0,
                        95.0,
                        418.0
                    ]
                },
                {
                    "text": "OR",
                    "bbox": [
                        99.0,
                        402.0,
                        119.0,
                        418.0
                    ]
                },
                {
                    "text": "SIZES:",
                    "bbox": [
                        124.0,
                        401.0,
                        172.0,
                        417.0
                    ]
                }
            ]
        },
        {
            "line_text": "LIST PRICE:",
            "line_bbox": [
                65.0,
                454.0,
                145.0,
                469.0
            ],
            "handwriting": 0,
            "words": [
                {
                    "text": "LIST",
                    "bbox": [
                        66.0,
                        455.0,
                        94.0,
                        470.0
                    ]
                },
                {
                    "text": "PRICE:",
                    "bbox": [
                        97.0,
                        455.0,
                        146.0,
                        470.0
                    ]
                }
            ]
        },
        {
            "line_text": "EXTENT OF",
            "line_bbox": [
                64.0,
                507.0,
                145.0,
                520.0
            ],
            "handwriting": 0,
            "words": [
                {
                    "text": "EXTENT",
                    "bbox": [
                        65.0,
                        507.0,
                        118.0,
                        521.0
                    ]
                },
                {
                    "text": "OF",
                    "bbox": [
                        122.0,
                        507.0,
                        141.0,
                        521.0
                    ]
                }
            ]
        },
        {
            "line_text": "DISTRIBUTION:",
            "line_bbox": [
                64.0,
                523.0,
                172.0,
                538.0
            ],
            "handwriting": 0,
            "words": [
                {
                    "text": "DISTRIBUTION:",
                    "bbox": [
                        65.0,
                        524.0,
                        172.0,
                        539.0
                    ]
                }
            ]
        },
        {
            "line_text": "OTHER",
            "line_bbox": [
                66.0,
                610.0,
                115.0,
                625.0
            ],
            "handwriting": 0,
            "words": [
                {
                    "text": "OTHER",
                    "bbox": [
                        67.0,
                        611.0,
                        112.0,
                        625.0
                    ]
                }
            ]
        },
        {
            "line_text": "INFORMATION:",
            "line_bbox": [
                64.0,
                628.0,
                170.0,
                643.0
            ],
            "handwriting": 0,
            "words": [
                {
                    "text": "INFORMATION:",
                    "bbox": [
                        65.0,
                        628.0,
                        171.0,
                        644.0
                    ]
                }
            ]
        },
        {
            "line_text": "SEE ATTACHMENT",
            "line_bbox": [
                236.0,
                626.0,
                362.0,
                641.0
            ],
            "handwriting": 0,
            "words": [
                {
                    "text": "SEE",
                    "bbox": [
                        237.0,
                        628.0,
                        261.0,
                        641.0
                    ]
                },
                {
                    "text": "ATTACHMENT",
                    "bbox": [
                        271.0,
                        627.0,
                        361.0,
                        641.0
                    ]
                }
            ]
        },
        {
            "line_text": "cc:",
            "line_bbox": [
                68.0,
                753.0,
                88.0,
                764.0
            ],
            "handwriting": 0,
            "words": [
                {
                    "text": "cc:",
                    "bbox": [
                        68.0,
                        753.0,
                        88.0,
                        764.0
                    ]
                }
            ]
        },
        {
            "line_text": "A. H. Tisch",
            "line_bbox": [
                64.0,
                767.0,
                139.0,
                782.0
            ],
            "handwriting": 0,
            "words": [
                {
                    "text": "A.",
                    "bbox": [
                        68.0,
                        768.0,
                        81.0,
                        782.0
                    ]
                },
                {
                    "text": "H.",
                    "bbox": [
                        83.0,
                        768.0,
                        100.0,
                        782.0
                    ]
                },
                {
                    "text": "Tisch",
                    "bbox": [
                        102.0,
                        768.0,
                        136.0,
                        782.0
                    ]
                }
            ]
        },
        {
            "line_text": "F. J. Schultz",
            "line_bbox": [
                223.0,
                765.0,
                306.0,
                781.0
            ],
            "handwriting": 0,
            "words": [
                {
                    "text": "F.",
                    "bbox": [
                        224.0,
                        766.0,
                        237.0,
                        781.0
                    ]
                },
                {
                    "text": "J.",
                    "bbox": [
                        240.0,
                        766.0,
                        253.0,
                        781.0
                    ]
                },
                {
                    "text": "Schultz",
                    "bbox": [
                        256.0,
                        767.0,
                        307.0,
                        781.0
                    ]
                }
            ]
        },
        {
            "line_text": "J. J. Tatulli",
            "line_bbox": [
                356.0,
                766.0,
                428.0,
                780.0
            ],
            "handwriting": 0,
            "words": [
                {
                    "text": "J.",
                    "bbox": [
                        357.0,
                        767.0,
                        369.0,
                        780.0
                    ]
                },
                {
                    "text": "J.",
                    "bbox": [
                        371.0,
                        766.0,
                        385.0,
                        780.0
                    ]
                },
                {
                    "text": "Tatulli",
                    "bbox": [
                        388.0,
                        766.0,
                        429.0,
                        781.0
                    ]
                }
            ]
        },
        {
            "line_text": "K. P. Augustyn",
            "line_bbox": [
                533.0,
                764.0,
                632.0,
                779.0
            ],
            "handwriting": 0,
            "words": [
                {
                    "text": "K.",
                    "bbox": [
                        533.0,
                        764.0,
                        547.0,
                        779.0
                    ]
                },
                {
                    "text": "P.",
                    "bbox": [
                        549.0,
                        765.0,
                        565.0,
                        779.0
                    ]
                },
                {
                    "text": "Augustyn",
                    "bbox": [
                        567.0,
                        766.0,
                        629.0,
                        780.0
                    ]
                }
            ]
        },
        {
            "line_text": "R. H. Orcutt",
            "line_bbox": [
                68.0,
                784.0,
                145.0,
                801.0
            ],
            "handwriting": 0,
            "words": [
                {
                    "text": "R.",
                    "bbox": [
                        68.0,
                        785.0,
                        80.0,
                        800.0
                    ]
                },
                {
                    "text": "H.",
                    "bbox": [
                        83.0,
                        785.0,
                        99.0,
                        800.0
                    ]
                },
                {
                    "text": "Orcutt",
                    "bbox": [
                        102.0,
                        786.0,
                        145.0,
                        801.0
                    ]
                }
            ]
        },
        {
            "line_text": "A. W. Spears",
            "line_bbox": [
                225.0,
                784.0,
                310.0,
                798.0
            ],
            "handwriting": 0,
            "words": [
                {
                    "text": "A.",
                    "bbox": [
                        225.0,
                        785.0,
                        238.0,
                        799.0
                    ]
                },
                {
                    "text": "W.",
                    "bbox": [
                        241.0,
                        785.0,
                        260.0,
                        799.0
                    ]
                },
                {
                    "text": "Spears",
                    "bbox": [
                        262.0,
                        785.0,
                        310.0,
                        799.0
                    ]
                }
            ]
        },
        {
            "line_text": "L. H. Kersh",
            "line_bbox": [
                356.0,
                784.0,
                431.0,
                798.0
            ],
            "handwriting": 0,
            "words": [
                {
                    "text": "L.",
                    "bbox": [
                        357.0,
                        784.0,
                        368.0,
                        798.0
                    ]
                },
                {
                    "text": "H.",
                    "bbox": [
                        370.0,
                        784.0,
                        387.0,
                        798.0
                    ]
                },
                {
                    "text": "Kersh",
                    "bbox": [
                        389.0,
                        784.0,
                        427.0,
                        798.0
                    ]
                }
            ]
        },
        {
            "line_text": "V. D. Lindsley",
            "line_bbox": [
                532.0,
                781.0,
                624.0,
                797.0
            ],
            "handwriting": 0,
            "words": [
                {
                    "text": "V.",
                    "bbox": [
                        533.0,
                        781.0,
                        545.0,
                        797.0
                    ]
                },
                {
                    "text": "D.",
                    "bbox": [
                        548.0,
                        782.0,
                        563.0,
                        797.0
                    ]
                },
                {
                    "text": "Lindsley",
                    "bbox": [
                        566.0,
                        782.0,
                        624.0,
                        797.0
                    ]
                }
            ]
        },
        {
            "line_text": "M. A. Peterson",
            "line_bbox": [
                67.0,
                802.0,
                164.0,
                817.0
            ],
            "handwriting": 0,
            "words": [
                {
                    "text": "M.",
                    "bbox": [
                        68.0,
                        802.0,
                        83.0,
                        817.0
                    ]
                },
                {
                    "text": "A.",
                    "bbox": [
                        85.0,
                        803.0,
                        100.0,
                        817.0
                    ]
                },
                {
                    "text": "Peterson",
                    "bbox": [
                        102.0,
                        803.0,
                        162.0,
                        817.0
                    ]
                }
            ]
        },
        {
            "line_text": "N. P. Ruffalo",
            "line_bbox": [
                224.0,
                802.0,
                308.0,
                816.0
            ],
            "handwriting": 0,
            "words": [
                {
                    "text": "N.",
                    "bbox": [
                        224.0,
                        802.0,
                        239.0,
                        816.0
                    ]
                },
                {
                    "text": "P.",
                    "bbox": [
                        241.0,
                        803.0,
                        257.0,
                        816.0
                    ]
                },
                {
                    "text": "Ruffalo",
                    "bbox": [
                        259.0,
                        802.0,
                        307.0,
                        816.0
                    ]
                }
            ]
        },
        {
            "line_text": "J. R. Slater",
            "line_bbox": [
                357.0,
                801.0,
                430.0,
                815.0
            ],
            "handwriting": 0,
            "words": [
                {
                    "text": "J.",
                    "bbox": [
                        358.0,
                        802.0,
                        368.0,
                        814.0
                    ]
                },
                {
                    "text": "R.",
                    "bbox": [
                        370.0,
                        802.0,
                        387.0,
                        815.0
                    ]
                },
                {
                    "text": "Slater",
                    "bbox": [
                        389.0,
                        802.0,
                        430.0,
                        815.0
                    ]
                }
            ]
        },
        {
            "line_text": "R. D. Hammer",
            "line_bbox": [
                533.0,
                799.0,
                626.0,
                814.0
            ],
            "handwriting": 0,
            "words": [
                {
                    "text": "R.",
                    "bbox": [
                        533.0,
                        800.0,
                        547.0,
                        814.0
                    ]
                },
                {
                    "text": "D.",
                    "bbox": [
                        549.0,
                        800.0,
                        565.0,
                        814.0
                    ]
                },
                {
                    "text": "Hammer",
                    "bbox": [
                        568.0,
                        800.0,
                        627.0,
                        814.0
                    ]
                }
            ]
        },
        {
            "line_text": "M. L. Orlowsky",
            "line_bbox": [
                66.0,
                819.0,
                165.0,
                835.0
            ],
            "handwriting": 0,
            "words": [
                {
                    "text": "M.",
                    "bbox": [
                        67.0,
                        820.0,
                        81.0,
                        835.0
                    ]
                },
                {
                    "text": "L.",
                    "bbox": [
                        84.0,
                        820.0,
                        98.0,
                        835.0
                    ]
                },
                {
                    "text": "Orlowsky",
                    "bbox": [
                        101.0,
                        820.0,
                        164.0,
                        836.0
                    ]
                }
            ]
        },
        {
            "line_text": "T. L. Achey",
            "line_bbox": [
                223.0,
                818.0,
                299.0,
                834.0
            ],
            "handwriting": 0,
            "words": [
                {
                    "text": "T.",
                    "bbox": [
                        225.0,
                        819.0,
                        237.0,
                        834.0
                    ]
                },
                {
                    "text": "L.",
                    "bbox": [
                        240.0,
                        819.0,
                        254.0,
                        834.0
                    ]
                },
                {
                    "text": "Achey",
                    "bbox": [
                        257.0,
                        820.0,
                        298.0,
                        835.0
                    ]
                }
            ]
        },
        {
            "line_text": "A. Pasheluk",
            "line_bbox": [
                357.0,
                818.0,
                436.0,
                833.0
            ],
            "handwriting": 0,
            "words": [
                {
                    "text": "A.",
                    "bbox": [
                        357.0,
                        818.0,
                        370.0,
                        833.0
                    ]
                },
                {
                    "text": "Pasheluk",
                    "bbox": [
                        372.0,
                        819.0,
                        434.0,
                        833.0
                    ]
                }
            ]
        },
        {
            "line_text": "91361993",
            "line_bbox": [
                735.0,
                825.0,
                750.0,
                898.0
            ],
            "handwriting": 0,
            "words": [
                {
                    "text": "91361993",
                    "bbox": [
                        735.0,
                        826.0,
                        751.0,
                        895.0
                    ]
                }
            ]
        },
        {
            "line_text": "L. Gordon",
            "line_bbox": [
                66.0,
                838.0,
                133.0,
                852.0
            ],
            "handwriting": 0,
            "words": [
                {
                    "text": "L.",
                    "bbox": [
                        67.0,
                        838.0,
                        79.0,
                        852.0
                    ]
                },
                {
                    "text": "Gordon",
                    "bbox": [
                        81.0,
                        838.0,
                        131.0,
                        852.0
                    ]
                }
            ]
        },
        {
            "line_text": "P. J. McCann",
            "line_bbox": [
                224.0,
                837.0,
                315.0,
                852.0
            ],
            "handwriting": 0,
            "words": [
                {
                    "text": "P.",
                    "bbox": [
                        225.0,
                        837.0,
                        238.0,
                        852.0
                    ]
                },
                {
                    "text": "J.",
                    "bbox": [
                        241.0,
                        837.0,
                        254.0,
                        852.0
                    ]
                },
                {
                    "text": "McCann",
                    "bbox": [
                        256.0,
                        837.0,
                        311.0,
                        852.0
                    ]
                }
            ]
        },
        {
            "line_text": "R. S. Goldbrenner",
            "line_bbox": [
                356.0,
                835.0,
                477.0,
                850.0
            ],
            "handwriting": 0,
            "words": [
                {
                    "text": "R.",
                    "bbox": [
                        356.0,
                        836.0,
                        370.0,
                        850.0
                    ]
                },
                {
                    "text": "S.",
                    "bbox": [
                        373.0,
                        836.0,
                        388.0,
                        850.0
                    ]
                },
                {
                    "text": "Goldbrenner",
                    "bbox": [
                        390.0,
                        836.0,
                        477.0,
                        851.0
                    ]
                }
            ]
        },
        {
            "line_text": "G. Telford",
            "line_bbox": [
                67.0,
                854.0,
                133.0,
                869.0
            ],
            "handwriting": 0,
            "words": [
                {
                    "text": "G.",
                    "bbox": [
                        68.0,
                        855.0,
                        82.0,
                        869.0
                    ]
                },
                {
                    "text": "Telford",
                    "bbox": [
                        85.0,
                        855.0,
                        131.0,
                        870.0
                    ]
                }
            ]
        },
        {
            "line_text": "A. J. Giacoio",
            "line_bbox": [
                224.0,
                854.0,
                310.0,
                870.0
            ],
            "handwriting": 0,
            "words": [
                {
                    "text": "A.",
                    "bbox": [
                        224.0,
                        855.0,
                        238.0,
                        870.0
                    ]
                },
                {
                    "text": "J.",
                    "bbox": [
                        241.0,
                        855.0,
                        254.0,
                        870.0
                    ]
                },
                {
                    "text": "Giacoio",
                    "bbox": [
                        257.0,
                        854.0,
                        309.0,
                        870.0
                    ]
                }
            ]
        },
        {
            "line_text": "N. Simeonidis",
            "line_bbox": [
                356.0,
                852.0,
                449.0,
                868.0
            ],
            "handwriting": 0,
            "words": [
                {
                    "text": "N.",
                    "bbox": [
                        357.0,
                        853.0,
                        371.0,
                        868.0
                    ]
                },
                {
                    "text": "Simeonidis",
                    "bbox": [
                        373.0,
                        853.0,
                        449.0,
                        868.0
                    ]
                }
            ]
        },
        {
            "line_text": "S. F. Smith",
            "line_bbox": [
                357.0,
                870.0,
                430.0,
                886.0
            ],
            "handwriting": 0,
            "words": [
                {
                    "text": "S.",
                    "bbox": [
                        358.0,
                        872.0,
                        370.0,
                        886.0
                    ]
                },
                {
                    "text": "F.",
                    "bbox": [
                        373.0,
                        872.0,
                        388.0,
                        886.0
                    ]
                },
                {
                    "text": "Smith",
                    "bbox": [
                        390.0,
                        871.0,
                        428.0,
                        886.0
                    ]
                }
            ]
        }
    ]
}